MANIFEST.in
README.rst
setup.cfg
setup.py
iterplus/__init__.py
iterplus/chainable.py
iterplus/index.py
iterplus/scan.py
iterplus/sliceable.py
iterplus.egg-info/PKG-INFO
iterplus.egg-info/SOURCES.txt
iterplus.egg-info/dependency_links.txt
iterplus.egg-info/requires.txt
iterplus.egg-info/top_level.txt