Metadata-Version: 1.0
Name: iterplus
Version: 0.2.5
Summary: iterplus provides functionality that extends itertools
Home-page: http://github.com/bebraw/iterplus
Author: Juho Vepsäläinen
Author-email: bebraw@gmail.com
License: MIT
Keywords: functional programming,itertools
Platform: UNKNOWN
Classifier: Development Status :: 3 - Alpha
Classifier: Intended Audience :: Developers
Classifier: License :: OSI Approved :: MIT License
Classifier: Natural Language :: English
Classifier: Operating System :: OS Independent
Classifier: Programming Language :: Python
Classifier: Topic :: Scientific/Engineering
Classifier: Topic :: Software Development
